reshape_helper/__init__.py
reshape_helper/schema_query.py
reshape_helper-0.1.0.dist-info/METADATA
reshape_helper-0.1.0.dist-info/WHEEL
reshape_helper-0.1.0.dist-info/licenses/LICENSE.md
reshape_helper-0.1.0.dist-info/RECORD
