Metadata-Version: 2.1
Name: reshape-helper
Version: 0.1.0
Summary: A Python helper library for applications using Reshape
Project-URL: Homepage, https://github.com/fabianlindfors/reshape-python
Project-URL: Bug Tracker, https://github.com/fabianlindfors/reshape-python/issues
Author-email: Fabian Lindfors <fabian@flapplabs.se>
License: MIT
Classifier: License :: OSI Approved :: MIT License
Classifier: Operating System :: OS Independent
Classifier: Programming Language :: Python :: 3
Requires-Python: >=3.4
Requires-Dist: natsort
Requires-Dist: toml
